[
  {
    "id": "010",
    "name": "稅課收入",
    "value": 126301,
    "children": [
      {
        "id": "010010",
        "name": "所得稅",
        "value": 7008,
        "children": [
          {
            "id": "010010010",
            "name": "營利事業所得稅",
            "value": 5489
          },
          {
            "id": "010010020",
            "name": "綜合所得稅",
            "value": 1519
          }
        ]
      },
      {
        "id": "010020",
        "name": "遺產及贈與稅",
        "value": 11853,
        "children": [
          {
            "id": "010020010",
            "name": "遺產稅",
            "value": 2556
          },
          {
            "id": "010020020",
            "name": "贈與稅",
            "value": 9297
          }
        ]
      },
      {
        "id": "010030",
        "name": "關稅",
        "value": 7627
      },
      {
        "id": "010040",
        "name": "貨物稅",
        "value": 2382
      },
      {
        "id": "010050",
        "name": "證券交易稅",
        "value": 4062
      },
      {
        "id": "010060",
        "name": "礦區稅",
        "value": 5918
      },
      {
        "id": "010070",
        "name": "期貨交易稅",
        "value": 5857
      },
      {
        "id": "010080",
        "name": "菸酒稅",
        "value": 9942
      },
      {
        "id": "010090",
        "name": "特種貨物及勞務稅",
        "value": 6177
      },
      {
        "id": "010100",
        "name": "營業稅",
        "value": 573
      },
      {
        "id": "010110",
        "name": "印花稅",
        "value": 2610
      },
      {
        "id": "010120",
        "name": "使用牌照稅",
        "value": 8607
      },
      {
        "id": "010130",
        "name": "土地稅",
        "value": 9967,
        "children": [
          {
            "id": "010130010",
            "name": "地價稅",
            "value": 6857
          },
          {
            "id": "010130020",
            "name": "土地增值稅",
            "value": 3110
          }
        ]
      },
      {
        "id": "010140",
        "name": "房屋稅",
        "value": 304
      },
      {
        "id": "010150",
        "name": "契稅",
        "value": 6553
      },
      {
        "id": "010160",
        "name": "娛樂稅",
        "value": 2220
      },
      {
        "id": "010170",
        "name": "統籌分配稅",
        "value": 10278,
        "children": [
          {
            "id": "010170010",
            "name": "普通統籌",
            "value": 1354
          },
          {
            "id": "010170020",
            "name": "特別統籌",
            "value": 8924
          }
        ]
      },
      {
        "id": "010180",
        "name": "特別稅課",
        "value": 8086
      },
      {
        "id": "010190",
        "name": "臨時稅課",
        "value": 8793
      },
      {
        "id": "010200",
        "name": "附加稅課",
        "value": 7484
      }
    ]
  },
  {
    "id": "020",
    "name": "獨占及專賣收入",
    "value": 3958,
    "children": [
      {
        "id": "020010",
        "name": "專賣利益",
        "value": 3958
      }
    ]
  },
  {
    "id": "030",
    "name": "工程受益費收入",
    "value": 3029,
    "children": [
      {
        "id": "030010",
        "name": "工程受益費收入",
        "value": 3029
      }
    ]
  },
  {
    "id": "040",
    "name": "罰款及賠償收入",
    "value": 32592,
    "children": [
      {
        "id": "040010",
        "name": "罰金罰鍰及怠金",
        "value": 13781,
        "children": [
          {
            "id": "040010010",
            "name": "罰金罰鍰",
            "value": 6966
          },
          {
            "id": "040010020",
            "name": "怠金",
            "value": 6815
          }
        ]
      },
      {
        "id": "040020",
        "name": "沒入及沒收財物",
        "value": 7037,
        "children": [
          {
            "id": "040020010",
            "name": "沒入金",
            "value": 5911
          },
          {
            "id": "040020020",
            "name": "沒收物變價",
            "value": 1126
          }
        ]
      },
      {
        "id": "040030",
        "name": "賠償收入",
        "value": 11774,
        "children": [
          {
            "id": "040030010",
            "name": "一般賠償收入",
            "value": 8399
          },
          {
            "id": "040030020",
            "name": "賠償求償收入",
            "value": 3375
          }
        ]
      }
    ]
  },
  {
    "id": "050",
    "name": "規費收入",
    "value": 98244,
    "children": [
      {
        "id": "050010",
        "name": "行政規費收入",
        "value": 25265,
        "children": [
          {
            "id": "050010010",
            "name": "審查費",
            "value": 1468
          },
          {
            "id": "050010020",
            "name": "證照費",
            "value": 9306
          },
          {
            "id": "050010030",
            "name": "登記費",
            "value": 3619
          },
          {
            "id": "050010040",
            "name": "考試報名費",
            "value": 9185
          },
          {
            "id": "050010050",
            "name": "許可費",
            "value": 1687
          }
        ]
      },
      {
        "id": "050020",
        "name": "司法規費收入",
        "value": 19389,
        "children": [
          {
            "id": "050020010",
            "name": "民事訴訟費",
            "value": 5733
          },
          {
            "id": "050020020",
            "name": "非訟事件費",
            "value": 6542
          },
          {
            "id": "050020030",
            "name": "公證費",
            "value": 6445
          },
          {
            "id": "050020040",
            "name": "行政訴訟費",
            "value": 669
          }
        ]
      },
      {
        "id": "050030",
        "name": "使用規費收入",
        "value": 53590,
        "children": [
          {
            "id": "050030010",
            "name": "汽車燃料使用費",
            "value": 4473
          },
          {
            "id": "050030020",
            "name": "通行費資料使用費",
            "value": 8828
          },
          {
            "id": "050030030",
            "name": "建教合作費",
            "value": 7250
          },
          {
            "id": "050030040",
            "name": "供應費",
            "value": 7152
          },
          {
            "id": "050030050",
            "name": "場地設施使用費",
            "value": 9704
          },
          {
            "id": "050030060",
            "name": "服務費",
            "value": 5877
          },
          {
            "id": "050030070",
            "name": "道路使用費",
            "value": 2960
          },
          {
            "id": "050030080",
            "name": "頻率及電信號碼使用費",
            "value": 7346
          }
        ]
      }
    ]
  },
  {
    "id": "060",
    "name": "信託管理收入",
    "value": 5148,
    "children": [
      {
        "id": "060010",
        "name": "信託管理收入",
        "value": 5148
      }
    ]
  },
  {
    "id": "070",
    "name": "財產收入",
    "value": 58684,
    "children": [
      {
        "id": "070010",
        "name": "財產孳息",
        "value": 11884,
        "children": [
          {
            "id": "070010010",
            "name": "利息收入",
            "value": 8848
          },
          {
            "id": "070010020",
            "name": "權利金",
            "value": 1602
          },
          {
            "id": "070010030",
            "name": "租金收入",
            "value": 1434
          }
        ]
      },
      {
        "id": "070020",
        "name": "財產售價財產作價",
        "value": 26137,
        "children": [
          {
            "id": "070020010",
            "name": "土地售價",
            "value": 186
          },
          {
            "id": "070020020",
            "name": "土地以外不動產售價",
            "value": 5646
          },
          {
            "id": "070020030",
            "name": "動產售價",
            "value": 7833
          },
          {
            "id": "070020040",
            "name": "有價證券售價",
            "value": 6031
          },
          {
            "id": "070020050",
            "name": "權利售價",
            "value": 6441
          }
        ]
      },
      {
        "id": "070030",
        "name": "投資收回",
        "value": 18610,
        "children": [
          {
            "id": "070030010",
            "name": "營業資本收回",
            "value": 4212
          },
          {
            "id": "070030020",
            "name": "非營業特種基金收回",
            "value": 6829
          },
          {
            "id": "070030030",
            "name": "投資資本收回",
            "value": 7569
          }
        ]
      },
      {
        "id": "070040",
        "name": "廢舊物資售價",
        "value": 2053
      }
    ]
  },
  {
    "id": "080",
    "name": "營業盈餘及事業收入",
    "value": 26615,
    "children": [
      {
        "id": "080010",
        "name": "營業基金盈餘繳庫",
        "value": 11652,
        "children": [
          {
            "id": "080010010",
            "name": "股息紅利繳庫",
            "value": 1949
          },
          {
            "id": "080010020",
            "name": "盈餘轉增資",
            "value": 9703
          }
        ]
      },
      {
        "id": "080020",
        "name": "非營業特種基金賸餘繳庫",
        "value": 3776,
        "children": [
          {
            "id": "080020010",
            "name": "賸餘繳庫",
            "value": 3776
          }
        ]
      },
      {
        "id": "080030",
        "name": "投資收益",
        "value": 11187,
        "children": [
          {
            "id": "080030010",
            "name": "投資股息紅利",
            "value": 7743
          },
          {
            "id": "080030020",
            "name": "股票買賣差價",
            "value": 3444
          }
        ]
      }
    ]
  },
  {
    "id": "090",
    "name": "補助及協助收入",
    "value": 18859,
    "children": [
      {
        "id": "090010",
        "name": "上級政府補助收入",
        "value": 9541,
        "children": [
          {
            "id": "090010010",
            "name": "一般性補助收入",
            "value": 2698
          },
          {
            "id": "090010020",
            "name": "計畫型補助收入",
            "value": 6843
          }
        ]
      },
      {
        "id": "090020",
        "name": "地方政府協助收入",
        "value": 9318
      }
    ]
  },
  {
    "id": "100",
    "name": "捐獻及贈與收入",
    "value": 13626,
    "children": [
      {
        "id": "100010",
        "name": "捐獻收入",
        "value": 5049,
        "children": [
          {
            "id": "100010010",
            "name": "一般捐獻",
            "value": 1110
          },
          {
            "id": "100010020",
            "name": "留本基金捐獻",
            "value": 629
          },
          {
            "id": "100010030",
            "name": "購置財產捐獻",
            "value": 3310
          }
        ]
      },
      {
        "id": "100020",
        "name": "贈與收入",
        "value": 8577,
        "children": [
          {
            "id": "100020010",
            "name": "物品贈與",
            "value": 161
          },
          {
            "id": "100020020",
            "name": "財產贈與",
            "value": 8416
          }
        ]
      }
    ]
  },
  {
    "id": "110",
    "name": "自治稅捐收入",
    "value": 489,
    "children": []
  },
  {
    "id": "120",
    "name": "其他收入",
    "value": 24193,
    "children": [
      {
        "id": "120010",
        "name": "學雜費收入",
        "value": 3584,
        "children": [
          {
            "id": "120010010",
            "name": "學雜費收入",
            "value": 3421
          },
          {
            "id": "120010020",
            "name": "學生活動費收入",
            "value": 163
          }
        ]
      },
      {
        "id": "120020",
        "name": "雜項收入",
        "value": 20609,
        "children": [
          {
            "id": "120020010",
            "name": "收回以前年度歲出",
            "value": 678
          },
          {
            "id": "120020020",
            "name": "車輛保管費",
            "value": 1298
          },
          {
            "id": "120020030",
            "name": "車輛移置費",
            "value": 8275
          },
          {
            "id": "120020040",
            "name": "廢棄物清理費",
            "value": 6827
          },
          {
            "id": "120020050",
            "name": "其他雜項收入",
            "value": 3531
          }
        ]
      }
    ]
  }
]