[{"name":"縣(市)議會主管","id":"010","value":"192709","adjustment":"0"},{"name":"縣(市)政府主管","id":"020","value":"18954664","adjustment":"0"},{"name":"民政局(處)主管","id":"040","value":"418564","adjustment":"0"},{"name":"教育局(處)主管","id":"050","value":"69188","adjustment":"0"},{"name":"農(產)(經濟)業(發展)、漁業局(處)主管","id":"060","value":"208644","adjustment":"0"},{"name":"地政局(處)主管","id":"080","value":"230288","adjustment":"0"},{"name":"稅捐稽徵處((地方、財政)稅務局)主管","id":"090","value":"364376","adjustment":"0"},{"name":"警察局主管","id":"100","value":"1989386","adjustment":"0"},{"name":"消防局主管","id":"110","value":"518473","adjustment":"0"},{"name":"環境保護局主管","id":"120","value":"464560","adjustment":"0"},{"name":"衛生局主管","id":"130","value":"1582119","adjustment":"0"},{"name":"文化(觀光)(傳播)局(處)主管","id":"140","value":"536212","adjustment":"0"},{"name":"統籌支撥科目(其他支出)","id":"160","value":"1044457","adjustment":"0"},{"name":"第二預備金","id":"180","value":"80000","adjustment":"0"}]