[
  {
    "name": "縣(市)議會主管",
    "id": "010",
    "value": 875199,
    "adjustment": 80288
  },
  {
    "name": "縣(市)政府主管",
    "id": "020",
    "value": 745855,
    "adjustment": 41418
  },
  {
    "name": "行政(管理)處、新聞(局)處主管",
    "id": "030",
    "value": 410965,
    "adjustment": 102154
  },
  {
    "name": "民政局(處)主管",
    "id": "040",
    "value": 686248,
    "adjustment": 149328
  },
  {
    "name": "教育局(處)主管",
    "id": "050",
    "value": 78484,
    "adjustment": 17136
  },
  {
    "name": "農(產)(經濟)業(發展)",
    "id": "060",
    "value": 597003,
    "adjustment": 141969
  },
  {
    "name": "社會(勞工)局(處)主管",
    "id": "070",
    "value": 912986,
    "adjustment": 186331
  },
  {
    "name": "漁業局(處)主管",
    "id": "080",
    "value": 936828,
    "adjustment": 183822
  },
  {
    "name": "地政局(處)主管",
    "id": "090",
    "value": 714425,
    "adjustment": 203653
  },
  {
    "name": "稅捐稽徵處|((地方、財政)稅務局)主管",
    "id": "100",
    "value": 883248,
    "adjustment": 176269
  },
  {
    "name": "警察局主管",
    "id": "110",
    "value": 424588,
    "adjustment": 38760
  },
  {
    "name": "消防局主管",
    "id": "120",
    "value": 595214,
    "adjustment": 60164
  },
  {
    "name": "環境保護局主管",
    "id": "130",
    "value": 659425,
    "adjustment": 30256
  },
  {
    "name": "衛生局主管",
    "id": "140",
    "value": 225870,
    "adjustment": 56636
  },
  {
    "name": "文化(觀光)(傳播)局(處)主管",
    "id": "150",
    "value": 773468,
    "adjustment": 95920
  },
  {
    "name": "其他局(處)主管",
    "id": "160",
    "value": 414711,
    "adjustment": 119568
  },
  {
    "name": "統支撥科目(其他支出)",
    "id": "170",
    "value": 475987,
    "adjustment": 13306
  },
  {
    "name": "調整公務員工待遇準備",
    "id": "180",
    "value": 779413,
    "adjustment": 188746
  },
  {
    "name": "第二預備金",
    "id": "190",
    "value": 76717,
    "adjustment": 20708
  }
]