[
  {
    "id": "010",
    "name": "稅課收入",
    "value": 116917,
    "children": [
      {
        "id": "010010",
        "name": "所得稅",
        "value": 13918,
        "children": [
          {
            "id": "010010010",
            "name": "營利事業所得稅",
            "value": 9565
          },
          {
            "id": "010010020",
            "name": "綜合所得稅",
            "value": 4353
          }
        ]
      },
      {
        "id": "010020",
        "name": "遺產及贈與稅",
        "value": 8288,
        "children": [
          {
            "id": "010020010",
            "name": "遺產稅",
            "value": 7240
          },
          {
            "id": "010020020",
            "name": "贈與稅",
            "value": 1048
          }
        ]
      },
      {
        "id": "010030",
        "name": "關稅",
        "value": 6108
      },
      {
        "id": "010040",
        "name": "貨物稅",
        "value": 7709
      },
      {
        "id": "010050",
        "name": "證券交易稅",
        "value": 9014
      },
      {
        "id": "010060",
        "name": "礦區稅",
        "value": 4106
      },
      {
        "id": "010070",
        "name": "期貨交易稅",
        "value": 3369
      },
      {
        "id": "010080",
        "name": "菸酒稅",
        "value": 4194
      },
      {
        "id": "010090",
        "name": "特種貨物及勞務稅",
        "value": 465
      },
      {
        "id": "010100",
        "name": "營業稅",
        "value": 1418
      },
      {
        "id": "010110",
        "name": "印花稅",
        "value": 4462
      },
      {
        "id": "010120",
        "name": "使用牌照稅",
        "value": 3708
      },
      {
        "id": "010130",
        "name": "土地稅",
        "value": 9209,
        "children": [
          {
            "id": "010130010",
            "name": "地價稅",
            "value": 6292
          },
          {
            "id": "010130020",
            "name": "土地增值稅",
            "value": 2917
          }
        ]
      },
      {
        "id": "010140",
        "name": "房屋稅",
        "value": 6278
      },
      {
        "id": "010150",
        "name": "契稅",
        "value": 9738
      },
      {
        "id": "010160",
        "name": "娛樂稅",
        "value": 9550
      },
      {
        "id": "010170",
        "name": "統籌分配稅",
        "value": 3528,
        "children": [
          {
            "id": "010170010",
            "name": "普通統籌",
            "value": 2852
          },
          {
            "id": "010170020",
            "name": "特別統籌",
            "value": 676
          }
        ]
      },
      {
        "id": "010180",
        "name": "特別稅課",
        "value": 4014
      },
      {
        "id": "010190",
        "name": "臨時稅課",
        "value": 1612
      },
      {
        "id": "010200",
        "name": "附加稅課",
        "value": 6229
      }
    ]
  },
  {
    "id": "020",
    "name": "獨占及專賣收入",
    "value": 9349,
    "children": [
      {
        "id": "020010",
        "name": "專賣利益",
        "value": 9349
      }
    ]
  },
  {
    "id": "030",
    "name": "工程受益費收入",
    "value": 371,
    "children": [
      {
        "id": "030010",
        "name": "工程受益費收入",
        "value": 371
      }
    ]
  },
  {
    "id": "040",
    "name": "罰款及賠償收入",
    "value": 27498,
    "children": [
      {
        "id": "040010",
        "name": "罰金罰鍰及怠金",
        "value": 6480,
        "children": [
          {
            "id": "040010010",
            "name": "罰金罰鍰",
            "value": 5334
          },
          {
            "id": "040010020",
            "name": "怠金",
            "value": 1146
          }
        ]
      },
      {
        "id": "040020",
        "name": "沒入及沒收財物",
        "value": 5037,
        "children": [
          {
            "id": "040020010",
            "name": "沒入金",
            "value": 4466
          },
          {
            "id": "040020020",
            "name": "沒收物變價",
            "value": 571
          }
        ]
      },
      {
        "id": "040030",
        "name": "賠償收入",
        "value": 15981,
        "children": [
          {
            "id": "040030010",
            "name": "一般賠償收入",
            "value": 6461
          },
          {
            "id": "040030020",
            "name": "賠償求償收入",
            "value": 9520
          }
        ]
      }
    ]
  },
  {
    "id": "050",
    "name": "規費收入",
    "value": 71363,
    "children": [
      {
        "id": "050010",
        "name": "行政規費收入",
        "value": 18531,
        "children": [
          {
            "id": "050010010",
            "name": "審查費",
            "value": 5073
          },
          {
            "id": "050010020",
            "name": "證照費",
            "value": 10
          },
          {
            "id": "050010030",
            "name": "登記費",
            "value": 1141
          },
          {
            "id": "050010040",
            "name": "考試報名費",
            "value": 3343
          },
          {
            "id": "050010050",
            "name": "許可費",
            "value": 8964
          }
        ]
      },
      {
        "id": "050020",
        "name": "司法規費收入",
        "value": 19275,
        "children": [
          {
            "id": "050020010",
            "name": "民事訴訟費",
            "value": 3479
          },
          {
            "id": "050020020",
            "name": "非訟事件費",
            "value": 2879
          },
          {
            "id": "050020030",
            "name": "公證費",
            "value": 4168
          },
          {
            "id": "050020040",
            "name": "行政訴訟費",
            "value": 8749
          }
        ]
      },
      {
        "id": "050030",
        "name": "使用規費收入",
        "value": 33557,
        "children": [
          {
            "id": "050030010",
            "name": "汽車燃料使用費",
            "value": 4112
          },
          {
            "id": "050030020",
            "name": "通行費資料使用費",
            "value": 6205
          },
          {
            "id": "050030030",
            "name": "建教合作費",
            "value": 5103
          },
          {
            "id": "050030040",
            "name": "供應費",
            "value": 6931
          },
          {
            "id": "050030050",
            "name": "場地設施使用費",
            "value": 7406
          },
          {
            "id": "050030060",
            "name": "服務費",
            "value": 1456
          },
          {
            "id": "050030070",
            "name": "道路使用費",
            "value": 347
          },
          {
            "id": "050030080",
            "name": "頻率及電信號碼使用費",
            "value": 1997
          }
        ]
      }
    ]
  },
  {
    "id": "060",
    "name": "信託管理收入",
    "value": 4219,
    "children": [
      {
        "id": "060010",
        "name": "信託管理收入",
        "value": 4219
      }
    ]
  },
  {
    "id": "070",
    "name": "財產收入",
    "value": 66679,
    "children": [
      {
        "id": "070010",
        "name": "財產孳息",
        "value": 13508,
        "children": [
          {
            "id": "070010010",
            "name": "利息收入",
            "value": 2977
          },
          {
            "id": "070010020",
            "name": "權利金",
            "value": 7600
          },
          {
            "id": "070010030",
            "name": "租金收入",
            "value": 2931
          }
        ]
      },
      {
        "id": "070020",
        "name": "財產售價財產作價",
        "value": 29718,
        "children": [
          {
            "id": "070020010",
            "name": "土地售價",
            "value": 5886
          },
          {
            "id": "070020020",
            "name": "土地以外不動產售價",
            "value": 8063
          },
          {
            "id": "070020030",
            "name": "動產售價",
            "value": 6604
          },
          {
            "id": "070020040",
            "name": "有價證券售價",
            "value": 3656
          },
          {
            "id": "070020050",
            "name": "權利售價",
            "value": 5509
          }
        ]
      },
      {
        "id": "070030",
        "name": "投資收回",
        "value": 22347,
        "children": [
          {
            "id": "070030010",
            "name": "營業資本收回",
            "value": 9324
          },
          {
            "id": "070030020",
            "name": "非營業特種基金收回",
            "value": 7804
          },
          {
            "id": "070030030",
            "name": "投資資本收回",
            "value": 5219
          }
        ]
      },
      {
        "id": "070040",
        "name": "廢舊物資售價",
        "value": 1106
      }
    ]
  },
  {
    "id": "080",
    "name": "營業盈餘及事業收入",
    "value": 22650,
    "children": [
      {
        "id": "080010",
        "name": "營業基金盈餘繳庫",
        "value": 5245,
        "children": [
          {
            "id": "080010010",
            "name": "股息紅利繳庫",
            "value": 1900
          },
          {
            "id": "080010020",
            "name": "盈餘轉增資",
            "value": 3345
          }
        ]
      },
      {
        "id": "080020",
        "name": "非營業特種基金賸餘繳庫",
        "value": 5397,
        "children": [
          {
            "id": "080020010",
            "name": "賸餘繳庫",
            "value": 5397
          }
        ]
      },
      {
        "id": "080030",
        "name": "投資收益",
        "value": 12008,
        "children": [
          {
            "id": "080030010",
            "name": "投資股息紅利",
            "value": 2898
          },
          {
            "id": "080030020",
            "name": "股票買賣差價",
            "value": 9110
          }
        ]
      }
    ]
  },
  {
    "id": "090",
    "name": "補助及協助收入",
    "value": 13224,
    "children": [
      {
        "id": "090010",
        "name": "上級政府補助收入",
        "value": 4452,
        "children": [
          {
            "id": "090010010",
            "name": "一般性補助收入",
            "value": 1936
          },
          {
            "id": "090010020",
            "name": "計畫型補助收入",
            "value": 2516
          }
        ]
      },
      {
        "id": "090020",
        "name": "地方政府協助收入",
        "value": 8772
      }
    ]
  },
  {
    "id": "100",
    "name": "捐獻及贈與收入",
    "value": 18803,
    "children": [
      {
        "id": "100010",
        "name": "捐獻收入",
        "value": 12583,
        "children": [
          {
            "id": "100010010",
            "name": "一般捐獻",
            "value": 3755
          },
          {
            "id": "100010020",
            "name": "留本基金捐獻",
            "value": 7287
          },
          {
            "id": "100010030",
            "name": "購置財產捐獻",
            "value": 1541
          }
        ]
      },
      {
        "id": "100020",
        "name": "贈與收入",
        "value": 6220,
        "children": [
          {
            "id": "100020010",
            "name": "物品贈與",
            "value": 3811
          },
          {
            "id": "100020020",
            "name": "財產贈與",
            "value": 2409
          }
        ]
      }
    ]
  },
  {
    "id": "110",
    "name": "自治稅捐收入",
    "value": 3987,
    "children": []
  },
  {
    "id": "120",
    "name": "其他收入",
    "value": 29561,
    "children": [
      {
        "id": "120010",
        "name": "學雜費收入",
        "value": 8407,
        "children": [
          {
            "id": "120010010",
            "name": "學雜費收入",
            "value": 7797
          },
          {
            "id": "120010020",
            "name": "學生活動費收入",
            "value": 610
          }
        ]
      },
      {
        "id": "120020",
        "name": "雜項收入",
        "value": 21154,
        "children": [
          {
            "id": "120020010",
            "name": "收回以前年度歲出",
            "value": 9366
          },
          {
            "id": "120020020",
            "name": "車輛保管費",
            "value": 305
          },
          {
            "id": "120020030",
            "name": "車輛移置費",
            "value": 545
          },
          {
            "id": "120020040",
            "name": "廢棄物清理費",
            "value": 4209
          },
          {
            "id": "120020050",
            "name": "其他雜項收入",
            "value": 6729
          }
        ]
      }
    ]
  }
]