[
  {
    "name": "縣(市)議會主管",
    "id": "010",
    "value": 663917,
    "adjustment": 6905
  },
  {
    "name": "縣(市)政府主管",
    "id": "020",
    "value": 841003,
    "adjustment": 57188
  },
  {
    "name": "行政(管理)處、新聞(局)處主管",
    "id": "030",
    "value": 53534,
    "adjustment": 7080
  },
  {
    "name": "民政局(處)主管",
    "id": "040",
    "value": 746117,
    "adjustment": 108446
  },
  {
    "name": "教育局(處)主管",
    "id": "050",
    "value": 907797,
    "adjustment": 7298
  },
  {
    "name": "農(產)(經濟)業(發展)",
    "id": "060",
    "value": 900029,
    "adjustment": 84638
  },
  {
    "name": "社會(勞工)局(處)主管",
    "id": "070",
    "value": 275112,
    "adjustment": 54187
  },
  {
    "name": "漁業局(處)主管",
    "id": "080",
    "value": 355600,
    "adjustment": 64154
  },
  {
    "name": "地政局(處)主管",
    "id": "090",
    "value": 42351,
    "adjustment": 4885
  },
  {
    "name": "稅捐稽徵處|((地方、財政)稅務局)主管",
    "id": "100",
    "value": 978996,
    "adjustment": 41245
  },
  {
    "name": "警察局主管",
    "id": "110",
    "value": 107562,
    "adjustment": 25613
  },
  {
    "name": "消防局主管",
    "id": "120",
    "value": 980636,
    "adjustment": 138452
  },
  {
    "name": "環境保護局主管",
    "id": "130",
    "value": 39873,
    "adjustment": 4522
  },
  {
    "name": "衛生局主管",
    "id": "140",
    "value": 842870,
    "adjustment": 89278
  },
  {
    "name": "文化(觀光)(傳播)局(處)主管",
    "id": "150",
    "value": 21396,
    "adjustment": 75
  },
  {
    "name": "其他局(處)主管",
    "id": "160",
    "value": 144374,
    "adjustment": 13212
  },
  {
    "name": "統支撥科目(其他支出)",
    "id": "170",
    "value": 721788,
    "adjustment": 192377
  },
  {
    "name": "調整公務員工待遇準備",
    "id": "180",
    "value": 362522,
    "adjustment": 93933
  },
  {
    "name": "第二預備金",
    "id": "190",
    "value": 838137,
    "adjustment": 161778
  }
]