[{"id":"01","name":"一般政務支出","value":"239969","children":[{"id":"0132","name":"行政支出","value":"131633"},{"id":"0133","name":"立法支出","value":"47826"},{"id":"0137","name":"民政支出","value":"53989"},{"id":"0140","name":"財務支出","value":"6521"}]},{"id":"02","name":"教育科學文化支出","value":"18472","children":[{"id":"0253","name":"文化支出","value":"18472"}]},{"id":"03","name":"經濟發展支出","value":"183510","children":[{"id":"0359","name":"其他經濟服務支出","value":"183510"}]},{"id":"04","name":"社會福利支出","value":"15392","children":[{"id":"0462","name":"社會救助支出","value":"6065"},{"id":"0463","name":"福利服務支出","value":"9327"}]},{"id":"05","name":"社區發展及環境保護支出","value":"41935","children":[{"id":"0571","name":"環境保護支出","value":"41935"}]},{"id":"06","name":"退休撫卹支出","value":"14706","children":[{"id":"0676","name":"退休撫卹給付支出","value":"14706"}]},{"id":"08","name":"補助及其他支出","value":"8628","children":[{"id":"0889","name":"其他支出","value":"8128"},{"id":"0890","name":"第二預備金","value":"500"}]}]