[
  {
    "name": "縣(市)議會主管",
    "id": "010",
    "value": 763207,
    "adjustment": 61883
  },
  {
    "name": "縣(市)政府主管",
    "id": "020",
    "value": 340063,
    "adjustment": 34455
  },
  {
    "name": "行政(管理)處、新聞(局)處主管",
    "id": "030",
    "value": 54044,
    "adjustment": 11825
  },
  {
    "name": "民政局(處)主管",
    "id": "040",
    "value": 701108,
    "adjustment": 26188
  },
  {
    "name": "教育局(處)主管",
    "id": "050",
    "value": 239719,
    "adjustment": 37070
  },
  {
    "name": "農(產)(經濟)業(發展)",
    "id": "060",
    "value": 866836,
    "adjustment": 167602
  },
  {
    "name": "社會(勞工)局(處)主管",
    "id": "070",
    "value": 611650,
    "adjustment": 145644
  },
  {
    "name": "漁業局(處)主管",
    "id": "080",
    "value": 542373,
    "adjustment": 83161
  },
  {
    "name": "地政局(處)主管",
    "id": "090",
    "value": 275478,
    "adjustment": 26495
  },
  {
    "name": "稅捐稽徵處|((地方、財政)稅務局)主管",
    "id": "100",
    "value": 147103,
    "adjustment": 13365
  },
  {
    "name": "警察局主管",
    "id": "110",
    "value": 33375,
    "adjustment": 1398
  },
  {
    "name": "消防局主管",
    "id": "120",
    "value": 517640,
    "adjustment": 28664
  },
  {
    "name": "環境保護局主管",
    "id": "130",
    "value": 564520,
    "adjustment": 125163
  },
  {
    "name": "衛生局主管",
    "id": "140",
    "value": 447874,
    "adjustment": 58044
  },
  {
    "name": "文化(觀光)(傳播)局(處)主管",
    "id": "150",
    "value": 404885,
    "adjustment": 64891
  },
  {
    "name": "其他局(處)主管",
    "id": "160",
    "value": 841855,
    "adjustment": 230280
  },
  {
    "name": "統支撥科目(其他支出)",
    "id": "170",
    "value": 96247,
    "adjustment": 26766
  },
  {
    "name": "調整公務員工待遇準備",
    "id": "180",
    "value": 201210,
    "adjustment": 39941
  },
  {
    "name": "第二預備金",
    "id": "190",
    "value": 257492,
    "adjustment": 2362
  }
]